pyfireconnect/__init__.py
pyfireconnect/pyfireconnect.py
sseclient/__init__.py
sseclient/sseclient.py
pyfireconnect-1.0.2.dist-info/METADATA
pyfireconnect-1.0.2.dist-info/WHEEL
pyfireconnect-1.0.2.dist-info/top_level.txt
pyfireconnect-1.0.2.dist-info/RECORD
