Metadata-Version: 2.1
Name: pyfireconnect
Version: 1.0.2
Summary: A simple python wrapper for the Firebase API compatible with Python 3.7, supports social signup
Home-page: https://github.com/quintuslabs/pyfireconnect
Author: Quintus Labs
License: MIT
Keywords: Firebase,Python 3
Platform: UNKNOWN
Classifier: Development Status :: 3 - Alpha
Classifier: Intended Audience :: Developers
Classifier: License :: OSI Approved :: MIT License
Classifier: Programming Language :: Python :: 3.5
Requires-Dist: requests (==2.22.0)
Requires-Dist: gcloud (==0.18.3)
Requires-Dist: oauth2client (==4.1.3)
Requires-Dist: requests-toolbelt (==0.9.1)
Requires-Dist: python-jwt (==3.2.4)
Requires-Dist: pycryptodome (==3.9.0)
Requires-Dist: urllib3 (==1.25.5)
